LICENSE
README.md
pyproject.toml
setup.cfg
setup.py
crypto_pay_api_sdk/__init__.py
crypto_pay_api_sdk/cryptopay.py
crypto_pay_api_sdk.egg-info/PKG-INFO
crypto_pay_api_sdk.egg-info/SOURCES.txt
crypto_pay_api_sdk.egg-info/dependency_links.txt
crypto_pay_api_sdk.egg-info/requires.txt
crypto_pay_api_sdk.egg-info/top_level.txt