Metadata-Version: 2.1
Name: crypto-pay-api-sdk
Version: 1.3.2
Summary: API for CryptoBot
Home-page: https://github.com/althonos/crypto-pay-api-sdk
Author: Vyacheslav Zhigulin
Author-email: muxellexum@gmail.com
License: MIT
Project-URL: Bug Tracker, https://github.com/althonos/crypto-pay-api-sdk/issues
Platform: UNKNOWN
Classifier: Intended Audience :: Developers
Classifier: License :: OSI Approved :: MIT License
Classifier: Operating System :: OS Independent
Classifier: Programming Language :: Python :: 3
Classifier: Topic :: Software Development :: Libraries :: Python Modules
Requires-Python: >=3.6
License-File: LICENSE
